scrapy_lastest/__init__.py
scrapy_lastest/item.py
scrapy_lastest/core/__init__.py
scrapy_lastest/core/downloader.py
scrapy_lastest/core/engine.py
scrapy_lastest/core/pipeline.py
scrapy_lastest/core/scheduler.py
scrapy_lastest/core/spider.py
scrapy_lastest/http/__init__.py
scrapy_lastest/http/request.py
scrapy_lastest/http/response.py
scrapy_lastest/middlewares/__init__.py
scrapy_lastest/middlewares/downloader_middlewares.py
scrapy_lastest/middlewares/spider_middlewares.py
scrapy_plus/__init__.py
scrapy_plus/item.py
scrapy_plus/core/__init__.py
scrapy_plus/core/downloader.py
scrapy_plus/core/engine.py
scrapy_plus/core/pipeline.py
scrapy_plus/core/scheduler.py
scrapy_plus/core/spider.py
scrapy_plus/http/__init__.py
scrapy_plus/http/request.py
scrapy_plus/http/response.py
scrapy_plus/middlewares/__init__.py
scrapy_plus/middlewares/downloader_middlewares.py
scrapy_plus/middlewares/spider_middlewares.py
scrapy_lastest-1.1.dist-info/LICENSE
scrapy_lastest-1.1.dist-info/METADATA
scrapy_lastest-1.1.dist-info/WHEEL
scrapy_lastest-1.1.dist-info/top_level.txt
scrapy_lastest-1.1.dist-info/RECORD
