Metadata-Version: 2.1
Name: scrapy-lastest
Version: 1.1
Summary: A mini spider framework, like Scrapy
Home-page: https://upload.pypi.org/legacy/
Author: ivedong
Author-email: your@email.com
License: MIT
Platform: UNKNOWN
Classifier: Programming Language :: Python
Classifier: Operating System :: Microsoft :: Windows
Classifier: Operating System :: Unix
Classifier: Programming Language :: Python :: 2.7
Classifier: Programming Language :: Python :: 3.4
Classifier: Programming Language :: Python :: 3.5
Classifier: Programming Language :: Python :: 3.6
Requires-Dist: requests (>=2.18.4)
Requires-Dist: six (>=1.11.0)
